icpReconstructor/__init__.py
icpReconstructor/casadi_reconstruction.py
icpReconstructor/epipolar_reconstruction.py
icpReconstructor/torch_reconstruction.py
icpReconstructor/utils.py
icpReconstructor/robots/__init__.py
icpReconstructor/robots/modular_bending_actuator.py
icpReconstructor-0.1.5.dist-info/LICENSE
icpReconstructor-0.1.5.dist-info/METADATA
icpReconstructor-0.1.5.dist-info/WHEEL
icpReconstructor-0.1.5.dist-info/top_level.txt
icpReconstructor-0.1.5.dist-info/RECORD
